{
  "admin": [
    {
      "username": "admin",
      "password": "test@123"
    }
  ],
  "users": [
    {
      "username": "jkhan",
      "password": "hjk",
      "email": "jkhan@gmail.com",
      "firstname": "Joseph",
      "lastname": "Kha",
      "id": 1
    },
    {
      "username": "amit",
      "password": "kljkljklj",
      "email": "amit@yahoo.com",
      "firstname": "Amit",
      "lastname": "Kumar",
      "id": 2
    },
    {
      "username": "kjklj",
      "password": "kljklj",
      "email": "jkhan1@gmail.com",
      "firstname": "Joseph",
      "lastname": "khan",
      "id": 6
    },
    {
      "username": "",
      "password": "",
      "email": "",
      "firstname": "",
      "lastname": "",
      "id": 7
    }
  ]
}